tipsql/postgresql/__init__.py
tipsql/postgresql/connection.py
tipsql/postgresql/cursor.py
tipsql/postgresql/datatype/__init__.py
tipsql/postgresql/datatype/number.py
tipsql/postgresql/datatype/varchar.py
tipsql/postgresql/information_schema/__init__.py
tipsql/postgresql/information_schema/columns.py
tipsql/postgresql/information_schema/tables.py
tipsql/postgresql/plugin.py
tipsql/postgresql/query/__init__.py
tipsql/postgresql/query/builder.py
tipsql/postgresql/relation.py
tipsql/postgresql/sync/__init__.py
tipsql/postgresql/sync/table.py
tipsql/postgresql/sync/table_generator.py
tipsql/postgresql/sync/table_generator.py.jinja
tipsql_postgresql-0.0.14.dist-info/METADATA
tipsql_postgresql-0.0.14.dist-info/WHEEL
tipsql_postgresql-0.0.14.dist-info/entry_points.txt
tipsql_postgresql-0.0.14.dist-info/RECORD
